aggienaut_common-0.1.6.dist-info/licenses/LICENSE
common/__init__.py
common/enums.py
common/errors.py
common/aggie_logging/__init__.py
common/aggie_logging/configs.py
common/aggie_logging/init_logger.py
common/aggie_logging/log_analysis.py
common/aggie_logging/log_maintenance.py
common/aggie_logging/logger_config.py
common/aggie_mqtt/__init__.py
common/aggie_mqtt/mqtt_broker.py
common/aggie_mqtt/mqtt_messaging.py
common/base_classes/base_hardware.py
common/base_classes/configs.py
common/command/__init__.py
common/command/command.py
common/command/configs.py
common/config_framework/__init__.py
common/config_framework/base_config.py
common/config_framework/config_manager.py
common/config_framework/load_configs.py
common/config_framework/precheck_configs.py
common/power_board/__init__.py
common/power_board/configs.py
common/power_board/power_api.py
common/power_board/power_board.py
common/power_board/power_board_singleton.py
common/power_board/power_switch.py
common/serial_comms/__init__.py
common/serial_comms/configs.py
common/serial_comms/radio.py
common/thread_handling/__init__.py
common/thread_handling/configs.py
common/thread_handling/safe_sleep.py
common/thread_handling/thread_handler.py
common/type_validation/__init__.py
common/type_validation/type_validation.py
common/usb_detect/__init__.py
common/usb_detect/configs.py
common/usb_detect/usb_detect.py
common/utils/__init__.py
common/utils/project_root.py
common/utils/time_it.py
aggienaut_common-0.1.6.dist-info/METADATA
aggienaut_common-0.1.6.dist-info/WHEEL
aggienaut_common-0.1.6.dist-info/top_level.txt
aggienaut_common-0.1.6.dist-info/RECORD
