Metadata-Version: 2.4
Name: aggienaut-common
Version: 0.1.6
Summary: A collection of common utilities and modules for AggieNaut projects
Author-email: AggieNaut Team <alecmkrueger@tamu.edu>
License: MIT
Project-URL: Homepage, https://github.com/Aggienaut-Apps/aggienaut-common
Project-URL: Bug Tracker, https://github.com/Aggienaut-Apps/aggienaut-common/issues
Project-URL: Source Code, https://github.com/Aggienaut-Apps/aggienaut-common
Classifier: Development Status :: 3 - Alpha
Classifier: Intended Audience :: Developers
Classifier: License :: OSI Approved :: MIT License
Classifier: Operating System :: OS Independent
Classifier: Programming Language :: Python :: 3
Classifier: Programming Language :: Python :: 3.8
Classifier: Programming Language :: Python :: 3.9
Classifier: Programming Language :: Python :: 3.10
Classifier: Programming Language :: Python :: 3.11
Classifier: Programming Language :: Python :: 3.12
Requires-Python: >=3.8
License-File: LICENSE
Requires-Dist: paho-mqtt>=1.6.0
Requires-Dist: pyserial>=3.5
Requires-Dist: toml>=0.10.2
Provides-Extra: dev
Requires-Dist: pytest>=6.0; extra == "dev"
Requires-Dist: pytest-cov; extra == "dev"
Requires-Dist: black; extra == "dev"
Requires-Dist: flake8; extra == "dev"
Dynamic: license-file
